dbt/adapters/rabbitbigquery/__init__.py
dbt/adapters/rabbitbigquery/__version__.py
dbt/adapters/rabbitbigquery/connections.py
dbt/adapters/rabbitbigquery/credentials.py
dbt/adapters/rabbitbigquery/impl.py
dbt/include/rabbitbigquery/__init__.py
dbt/include/rabbitbigquery/dbt_project.yml
dbt/include/rabbitbigquery/macros/adapters.sql
dbt/include/rabbitbigquery/macros/etc.sql
dbt/include/rabbitbigquery/macros/metadata.sql
dbt/include/rabbitbigquery/macros/adapters/apply_grants.sql
dbt/include/rabbitbigquery/macros/adapters/columns.sql
dbt/include/rabbitbigquery/macros/catalog/by_relation.sql
dbt/include/rabbitbigquery/macros/catalog/by_schema.sql
dbt/include/rabbitbigquery/macros/catalog/catalog.sql
dbt/include/rabbitbigquery/macros/materializations/clone.sql
dbt/include/rabbitbigquery/macros/materializations/copy.sql
dbt/include/rabbitbigquery/macros/materializations/incremental.sql
dbt/include/rabbitbigquery/macros/materializations/materialized_view.sql
dbt/include/rabbitbigquery/macros/materializations/seed.sql
dbt/include/rabbitbigquery/macros/materializations/snapshot.sql
dbt/include/rabbitbigquery/macros/materializations/table.sql
dbt/include/rabbitbigquery/macros/materializations/view.sql
dbt/include/rabbitbigquery/macros/materializations/functions/aggregate.sql
dbt/include/rabbitbigquery/macros/materializations/functions/scalar.sql
dbt/include/rabbitbigquery/macros/materializations/incremental_strategy/common.sql
dbt/include/rabbitbigquery/macros/materializations/incremental_strategy/insert_overwrite.sql
dbt/include/rabbitbigquery/macros/materializations/incremental_strategy/merge.sql
dbt/include/rabbitbigquery/macros/materializations/incremental_strategy/microbatch.sql
dbt/include/rabbitbigquery/macros/materializations/incremental_strategy/time_ingestion_tables.sql
dbt/include/rabbitbigquery/macros/materializations/models/incremental/on_schema_change.sql
dbt/include/rabbitbigquery/macros/python_model/python.sql
dbt_rabbit_bigquery-1.1.6.1.11.0.dist-info/licenses/LICENSE
dbt_rabbit_bigquery-1.1.6.1.11.0.dist-info/METADATA
dbt_rabbit_bigquery-1.1.6.1.11.0.dist-info/WHEEL
dbt_rabbit_bigquery-1.1.6.1.11.0.dist-info/entry_points.txt
dbt_rabbit_bigquery-1.1.6.1.11.0.dist-info/top_level.txt
dbt_rabbit_bigquery-1.1.6.1.11.0.dist-info/RECORD
